[
  {
    "Feature": "basket_icon_click",
    "Mean": 0.09915
  },
  {
    "Feature": "basket_add_list",
    "Mean": 0.07452
  },
  {
    "Feature": "basket_add_detail",
    "Mean": 0.11292
  },
  {
    "Feature": "sort_by",
    "Mean": 0.03685
  },
  {
    "Feature": "image_picker",
    "Mean": 0.02673
  },
  {
    "Feature": "account_page_click",
    "Mean": 0.00357
  },
  {
    "Feature": "promo_banner_click",
    "Mean": 0.01621
  },
  {
    "Feature": "detail_wishlist_add",
    "Mean": 0.00351
  },
  {
    "Feature": "list_size_dropdown",
    "Mean": 0.23036
  },
  {
    "Feature": "closed_minibasket_click",
    "Mean": 0.01728
  },
  {
    "Feature": "checked_delivery_detail",
    "Mean": 0.06287
  },
  {
    "Feature": "checked_returns_detail",
    "Mean": 0.00918
  },
  {
    "Feature": "sign_in",
    "Mean": 0.08881
  },
  {
    "Feature": "saw_checkout",
    "Mean": 0.08009
  },
  {
    "Feature": "saw_sizecharts",
    "Mean": 0.00039
  },
  {
    "Feature": "saw_delivery",
    "Mean": 0.00554
  },
  {
    "Feature": "saw_account_upgrade",
    "Mean": 0.0011
  },
  {
    "Feature": "saw_homepage",
    "Mean": 0.29002
  },
  {
    "Feature": "device_mobile",
    "Mean": 0.68071
  },
  {
    "Feature": "device_computer",
    "Mean": 0.19422
  },
  {
    "Feature": "device_tablet",
    "Mean": 0.12836
  },
  {
    "Feature": "returning_user",
    "Mean": 0.53492
  },
  {
    "Feature": "loc_uk",
    "Mean": 0.93322
  }
]